ifunctions/__init__.py
ifunctions/folder_create.py
ifunctions/icontains.py
ifunctions/ijoin.py
ifunctions/iopen.py
ifunctions/pip_freeze_without_version.py
ifunctions/print_to_last_line.py
ifunctions/random_bool.py
ifunctions/set_timeout.py
ifunctions/idjango/manage.py
ifunctions/igit/command.py
ifunctions-0.2.8.dist-info/entry_points.txt
ifunctions-0.2.8.dist-info/WHEEL
ifunctions-0.2.8.dist-info/METADATA
ifunctions-0.2.8.dist-info/RECORD
