Metadata-Version: 2.4
Name: ifunctions
Version: 0.2.8
Summary: 100% Python native — tanpa ketergantungan pada library pihak ketiga.
Author-email: arbadzukhron <dzukhronufiaarba@gmail.com>
Requires-Python: >=3.12
